agentwerkstatt/CI-CD-SETUP.md
agentwerkstatt/CONTRIBUTING.md
agentwerkstatt/MUSIC.md
agentwerkstatt/README.md
agentwerkstatt/ROADMAP.md
agentwerkstatt/__init__.py
agentwerkstatt/_version.py
agentwerkstatt/agent.py
agentwerkstatt/cli.py
agentwerkstatt/config.py
agentwerkstatt/interfaces.py
agentwerkstatt/docs/api-reference.md
agentwerkstatt/docs/architecture.md
agentwerkstatt/docs/configuration.md
agentwerkstatt/docs/development.md
agentwerkstatt/docs/getting-started.md
agentwerkstatt/docs/index.md
agentwerkstatt/examples/EXAMPLE.md
agentwerkstatt/llms/__init__.py
agentwerkstatt/llms/base.py
agentwerkstatt/llms/claude.py
agentwerkstatt/llms/mock.py
agentwerkstatt/services/__init__.py
agentwerkstatt/services/conversation_handler.py
agentwerkstatt/services/langfuse_service.py
agentwerkstatt/services/memory_service.py
agentwerkstatt/services/tool_executor.py
agentwerkstatt/third_party/Dockerfile.mem0
agentwerkstatt/third_party/LANGFUSE_INTEGRATION.md
agentwerkstatt/third_party/LANGFUSE_SETUP.md
agentwerkstatt/third_party/MEM0_SETUP.md
agentwerkstatt/third_party/docker-compose.yaml
agentwerkstatt/tools/__init__.py
agentwerkstatt/tools/base.py
agentwerkstatt/tools/discovery.py
agentwerkstatt/tools/websearch.py
agentwerkstatt-0.1.15.dist-info/METADATA
agentwerkstatt-0.1.15.dist-info/WHEEL
agentwerkstatt-0.1.15.dist-info/entry_points.txt
agentwerkstatt-0.1.15.dist-info/top_level.txt
agentwerkstatt-0.1.15.dist-info/RECORD
