Metadata-Version: 2.4
Name: agentwerkstatt
Version: 0.1.15
Summary: AgentWerkstatt, a minimalistic agentic framework
Author: Hannes Hapke
Project-URL: Homepage, https://github.com/hanneshapke/agentwerkstatt
Project-URL: Documentation, https://github.com/hanneshapke/agentwerkstatt#readme
Project-URL: Repository, https://github.com/hanneshapke/agentwerkstatt.git
Project-URL: Bug Tracker, https://github.com/hanneshapke/agentwerkstatt/issues
Project-URL: Discussions, https://github.com/hanneshapke/agentwerkstatt/discussions
Project-URL: Contributing, https://github.com/hanneshapke/agentwerkstatt/blob/main/CONTRIBUTING.md
Keywords: ai,agent,minimalistic
Classifier: Development Status :: 3 - Alpha
Classifier: Intended Audience :: Developers
Classifier: License :: OSI Approved :: MIT License
Classifier: Operating System :: OS Independent
Classifier: Programming Language :: Python :: 3
Classifier: Programming Language :: Python :: 3.10
Classifier: Programming Language :: Python :: 3.11
Classifier: Programming Language :: Python :: 3.12
Classifier: Topic :: Software Development :: Libraries :: Python Modules
Classifier: Topic :: System :: Filesystems
Classifier: Topic :: Scientific/Engineering :: Artificial Intelligence
Requires-Python: >=3.10
Requires-Dist: httpx>=0.24.0
Requires-Dist: python-dotenv>=1.0.0
Requires-Dist: absl-py>=1.0.0
Requires-Dist: PyYAML>=6.0.0
Provides-Extra: tracing
Requires-Dist: langfuse>=3.2.1; extra == "tracing"
Provides-Extra: memory
Requires-Dist: mem0ai>=0.1.115; extra == "memory"
Provides-Extra: dev
Requires-Dist: pytest>=7.0.0; extra == "dev"
Requires-Dist: pytest-cov>=4.0.0; extra == "dev"
Requires-Dist: pytest-mock>=3.10.0; extra == "dev"
Requires-Dist: ruff>=0.1.0; extra == "dev"
Requires-Dist: mypy>=1.0.0; extra == "dev"
Requires-Dist: pre-commit>=3.0.0; extra == "dev"
Provides-Extra: observability
Requires-Dist: langfuse>=3.2.1; extra == "observability"
